Metadata-Version: 2.1
Name: aiotranslate
Version: 0.0.1
Summary: Free Google translate module that uses async/await syntax.
Home-page: https://github.com/5elenay/aiotranslate/
Author: 5elenay
Author-email: 
License: GNU General Public License v3 (GPLv3)
Keywords: translate
Platform: UNKNOWN
Classifier: Development Status :: 5 - Production/Stable
Classifier: Intended Audience :: Developers
Classifier: Operating System :: Unix
Classifier: License :: OSI Approved :: GNU General Public License v3 (GPLv3)
Classifier: Programming Language :: Python :: 3
